fish_dbjob/__init__.py
fish_dbjob/cli.py
fish_dbjob/config.py
fish_dbjob/services/__init__.py
fish_dbjob/services/jobs.py
fish_dbjob/services/permissions.py
fish_dbjob/services/version.py
fish_dbjob-0.2.10.dist-info/entry_points.txt
fish_dbjob-0.2.10.dist-info/WHEEL
fish_dbjob-0.2.10.dist-info/METADATA
fish_dbjob-0.2.10.dist-info/RECORD
